ekaros/__cli__.py
ekaros/__init__.py
ekaros/_version.py
ekaros/conf/__init__.py
ekaros/conf/about/ekaros.yaml
ekaros/project.toml
ekaros/py.typed
ekaros-0.1.9.dist-info/LICENSE
ekaros-0.1.9.dist-info/METADATA
ekaros-0.1.9.dist-info/WHEEL
ekaros-0.1.9.dist-info/entry_points.txt
ekaros-0.1.9.dist-info/RECORD
