Metadata-Version: 2.1
Name: ekaros
Version: 0.1.9
Summary: A Python Library for Generative AI Art
Home-page: https://ekaros.entelecheia.ai
License: MIT
Author: Young Joon Lee
Author-email: entelecheia@hotmail.com
Requires-Python: >=3.8.1,<3.12
Classifier: License :: OSI Approved :: MIT License
Classifier: Programming Language :: Python :: 3
Classifier: Programming Language :: Python :: 3.9
Classifier: Programming Language :: Python :: 3.10
Classifier: Programming Language :: Python :: 3.11
Requires-Dist: hyfi (>=1.12.5,<2.0.0)
Project-URL: Repository, https://github.com/entelecheia/ekaros
